streprogen/__init__.py
streprogen/day.py
streprogen/diet.py
streprogen/exercises.py
streprogen/mealplan.py
streprogen/modeling.py
streprogen/optimization.py
streprogen/program.py
streprogen/sampling.py
streprogen/utils.py
streprogen/templates/mealplan_template.txt
streprogen/templates/program_template.html
streprogen/templates/program_template.tex
streprogen/templates/program_template.txt
streprogen/tests/test_api.py
streprogen/tests/test_modeling.py
streprogen/tests/test_optimization.py
streprogen/tests/test_sampling.py
streprogen-4.1.0.dist-info/licenses/LICENSE
streprogen-4.1.0.dist-info/METADATA
streprogen-4.1.0.dist-info/WHEEL
streprogen-4.1.0.dist-info/top_level.txt
streprogen-4.1.0.dist-info/RECORD
