Metadata-Version: 2.4
Name: streprogen
Version: 4.1.0
Summary: The Python strength program generator.
Author-email: Tommy Odland <tommy.odland@gmail.com>
License:                     GNU GENERAL PUBLIC LICENSE
Project-URL: Homepage, https://github.com/tommyod/streprogen
Project-URL: Repository, https://github.com/tommyod/streprogen.git
Keywords: strength,training,health,fitness,generator,weightlifting,powerlifting,exercise
Classifier: Development Status :: 4 - Beta
Classifier: Intended Audience :: End Users/Desktop
Classifier: Intended Audience :: Healthcare Industry
Classifier: License :: OSI Approved :: GNU General Public License v3 (GPLv3)
Classifier: Programming Language :: Python :: 3.9
Classifier: Programming Language :: Python :: 3.10
Classifier: Programming Language :: Python :: 3.11
Classifier: Programming Language :: Python :: 3.12
Classifier: Programming Language :: Python :: 3.13
Requires-Python: >=3.9
License-File: LICENSE
Requires-Dist: jinja2>=2.11.2
Requires-Dist: ortools>=7.7.7810
Dynamic: license-file
